torchidl/__init__.py
torchidl/implicit_base_model.py
torchidl/implicit_function.py
torchidl/implicit_rnn_model.py
torchidl/py.typed
torchidl/sim/__init__.py
torchidl/sim/sim.py
torchidl/sim/utils.py
torchidl/sim/solvers/__init__.py
torchidl/sim/solvers/admm_consensus.py
torchidl/sim/solvers/admm_consensus_multigpu.py
torchidl/sim/solvers/cvx.py
torchidl/sim/solvers/least_square.py
torchidl/sim/solvers/projected_gd_lowrank.py
torchidl/sim/solvers/solver.py
torchidl-0.0.4.dist-info/METADATA
torchidl-0.0.4.dist-info/WHEEL
torchidl-0.0.4.dist-info/licenses/LICENSE
torchidl-0.0.4.dist-info/RECORD
