Metadata-Version: 2.4
Name: torchidl
Version: 0.0.4
Summary: Official package of Implicit Deep Learning and State-driven Implicit Models
Project-URL: Documentation, https://implicit-deep-learning.readthedocs.io/en/latest/
Project-URL: Repository, https://github.com/HoangP8/Implicit-Deep-Learning
Project-URL: Issues, https://github.com/HoangP8/Implicit-Deep-Learning/issues
Author-email: Hoang Phan <21hoang.p@vinuni.edu.vn>, Bao Tran <21bao.tq@vinuni.edu.vn>, Chi Nguyen <22chi.nh@vinuni.edu.vn>, Bao Truong <21bao.tg@vinuni.edu.vn>, Thanh Tran <21thanh.tq@vinuni.edu.vn>, Khai Nguyen <khai.nx@vinuni.edu.vn>, Hong Chu <hong.ctm@vinuni.edu.vn>, Laurent El Ghaoui <laurent.eg@vinuni.edu.vn>
Maintainer-email: Hoang Phan <21hoang.p@vinuni.edu.vn>, Bao Tran <21bao.tq@vinuni.edu.vn>
License: MIT License
License-File: LICENSE
Classifier: Development Status :: 4 - Beta
Classifier: Intended Audience :: Developers
Requires-Python: >=3.10
Requires-Dist: cvxpy>=1.4.2
Requires-Dist: matplotlib>=3.7.0
Requires-Dist: mosek>=10.1.28
Requires-Dist: numpy>=1.26.4
Requires-Dist: scikit-learn>=1.2.0
Requires-Dist: scipy>=1.11.4
Requires-Dist: sphinx>=7.0.0
Requires-Dist: torch>=1.13.0
Requires-Dist: torchvision>=0.14.0
Requires-Dist: tqdm>=4.66.2
Provides-Extra: docs
Requires-Dist: furo>=2024.1.29; extra == 'docs'
Requires-Dist: sphinx-autobuild>=2024.1.1; extra == 'docs'
Requires-Dist: sphinx-autodoc-typehints>=1.22.0; extra == 'docs'
Requires-Dist: sphinx-copybutton>=0.5.0; extra == 'docs'
Requires-Dist: sphinx-markdown-tables>=0.0.17; extra == 'docs'
Requires-Dist: sphinx>=7.0.0; extra == 'docs'
Requires-Dist: sphinxemoji>=0.2.0; extra == 'docs'
